shipctl/__init__.py
shipctl/__main__.py
shipctl/click_options.py
shipctl/config.py
shipctl/oci_download.py
shipctl/oci_upload.py
shipctl/shipctl_client.py
shipctl-1.0.0.dist-info/LICENSE
shipctl-1.0.0.dist-info/METADATA
shipctl-1.0.0.dist-info/WHEEL
shipctl-1.0.0.dist-info/entry_points.txt
shipctl-1.0.0.dist-info/RECORD
