Metadata-Version: 2.3
Name: shipctl
Version: 1.0.0
Summary: Upload artifacts to OCI registry
License: Apache-2.0
Keywords: oci,automation,artifacts
Author: Alexander Kharkevich
Author-email: alex@kharkevich.org
Maintainer: Alexander Kharkevich
Maintainer-email: alex@kharkevich.org
Requires-Python: >=3.12, <3.13.dev0
Classifier: Intended Audience :: Developers
Classifier: Programming Language :: Python :: 3.12
Classifier: Operating System :: OS Independent
Requires-Dist: click (<9.0.0)
Requires-Dist: oras[ecr] (==0.2.37)
Requires-Dist: python-dotenv (<2)
Project-URL: Bug Tracker, https://github.com/mlflow-oidc/shipctl/issues
Project-URL: Documentation, https://mlflow-oidc.github.io/shipctl/
Project-URL: Homepage, https://github.com/mlflow-oidc/shipctl
Project-URL: Source Code, https://github.com/mlflow-oidc/shipctl/
